xaero2/__main__.py
xaero2/charger.py
xaero2/mylog.py
xaero2/test_conn.py
xaero2/time_tools.py
xaero2-0.0.1.dist-info/METADATA
xaero2-0.0.1.dist-info/WHEEL
xaero2-0.0.1.dist-info/top_level.txt
xaero2-0.0.1.dist-info/RECORD
